spitch/__init__.py
spitch/_base_client.py
spitch/_client.py
spitch/_compat.py
spitch/_constants.py
spitch/_exceptions.py
spitch/_files.py
spitch/_models.py
spitch/_qs.py
spitch/_resource.py
spitch/_response.py
spitch/_streaming.py
spitch/_types.py
spitch/_version.py
spitch/pagination.py
spitch/py.typed
spitch/_utils/__init__.py
spitch/_utils/_compat.py
spitch/_utils/_datetime_parse.py
spitch/_utils/_logs.py
spitch/_utils/_proxy.py
spitch/_utils/_reflection.py
spitch/_utils/_resources_proxy.py
spitch/_utils/_streams.py
spitch/_utils/_sync.py
spitch/_utils/_transform.py
spitch/_utils/_typing.py
spitch/_utils/_utils.py
spitch/lib/.keep
spitch/resources/__init__.py
spitch/resources/files.py
spitch/resources/jobs.py
spitch/resources/speech.py
spitch/resources/text.py
spitch/types/__init__.py
spitch/types/diacritics.py
spitch/types/file.py
spitch/types/file_download_params.py
spitch/types/file_download_response.py
spitch/types/file_list_params.py
spitch/types/file_upload_params.py
spitch/types/file_usage.py
spitch/types/files.py
spitch/types/job.py
spitch/types/job_list_params.py
spitch/types/jobs.py
spitch/types/speech_generate_params.py
spitch/types/speech_transcribe_params.py
spitch/types/text_tone_mark_params.py
spitch/types/text_translate_params.py
spitch/types/transcription.py
spitch/types/translation.py
spitch-1.41.1.dist-info/METADATA
spitch-1.41.1.dist-info/WHEEL
spitch-1.41.1.dist-info/licenses/LICENSE
spitch-1.41.1.dist-info/RECORD
